pyfamsa/__init__.py
pyfamsa/_famsa.pxd
pyfamsa/_famsa.pyd
pyfamsa/_famsa.pyi
pyfamsa/_famsa.pyx
pyfamsa/CMakeLists.txt
pyfamsa/py.typed
pyfamsa/tests/__init__.py
pyfamsa/tests/__main__.py
pyfamsa/tests/data/__init__.py
pyfamsa/tests/data/adeno_fiber.faa
pyfamsa/tests/data/adeno_fiber.p1.afa
pyfamsa/tests/data/adeno_fiber.p2.afa
pyfamsa/tests/data/adeno_fiber.sl.afa
pyfamsa/tests/data/adeno_fiber.sl.nwk
pyfamsa/tests/data/adeno_fiber.upgma.afa
pyfamsa/tests/data/adeno_fiber.upgma.nwk
pyfamsa/tests/data/adeno_fiber.upgma.pp.afa
pyfamsa/tests/data/hemopexin.faa
pyfamsa/tests/data/hemopexin.medoid-nj.afa
pyfamsa/tests/data/hemopexin.medoid-nj.nwk
pyfamsa/tests/data/hemopexin.medoid-sl.afa
pyfamsa/tests/data/hemopexin.medoid-sl.nwk
pyfamsa/tests/data/hemopexin.medoid-slink.nwk
pyfamsa/tests/data/hemopexin.medoid-upgma.afa
pyfamsa/tests/data/hemopexin.medoid-upgma.nwk
pyfamsa/tests/fasta.py
pyfamsa/tests/requirements.txt
pyfamsa/tests/test_aligner.py
pyfamsa/tests/test_alignment.py
pyfamsa/tests/test_doctest.py
pyfamsa/tests/test_sequence.py
pyfamsa-0.6.2.dist-info/METADATA
pyfamsa-0.6.2.dist-info/WHEEL
pyfamsa-0.6.2.dist-info/licenses/COPYING
pyfamsa-0.6.2.dist-info/RECORD
