Metadata-Version: 2.2
Name: pyfamsa
Version: 0.6.2
Summary: Cython bindings and Python interface to FAMSA, an algorithm for ultra-scale multiple sequence alignments.
Keywords: bioinformatics,sequence,alignment,protein,MSA
Author-Email: Martin Larralde <martin.larralde@embl.de>
License:                     GNU GENERAL PUBLIC LICENSE
Classifier: Development Status :: 4 - Beta
Classifier: Intended Audience :: Developers
Classifier: Intended Audience :: Science/Research
Classifier: License :: OSI Approved :: GNU General Public License v3 (GPLv3)
Classifier: Operating System :: OS Independent
Classifier: Programming Language :: C++
Classifier: Programming Language :: Cython
Classifier: Programming Language :: Python :: 3.8
Classifier: Programming Language :: Python :: 3.9
Classifier: Programming Language :: Python :: 3.10
Classifier: Programming Language :: Python :: 3.11
Classifier: Programming Language :: Python :: 3.12
Classifier: Programming Language :: Python :: 3.13
Classifier: Programming Language :: Python :: 3.14
Classifier: Programming Language :: Python :: Implementation :: CPython
Classifier: Programming Language :: Python :: Implementation :: PyPy
Classifier: Topic :: Scientific/Engineering :: Bio-Informatics
Classifier: Topic :: Scientific/Engineering :: Medical Science Apps.
Classifier: Typing :: Typed
Project-URL: Homepage, https://github.com/althonos/pyfamsa/
Project-URL: Documentation, https://pyfamsa.readthedocs.io/en/stable/
Project-URL: Bug Tracker, https://github.com/althonos/pyfamsa/issues
Project-URL: Changelog, https://github.com/althonos/pyfamsa/blob/master/CHANGELOG.md
Project-URL: Coverage, https://codecov.io/gh/althonos/pyfamsa/
Project-URL: Builds, https://github.com/althonos/pyfamsa/actions
Project-URL: PyPI, https://pypi.org/project/pyfamsa
Requires-Python: >=3.8
Requires-Dist: scoring-matrices~=0.3.0
Provides-Extra: test
Requires-Dist: importlib-resources; python_version < "3.9" and extra == "test"
